sq_codec/__about__.py
sq_codec/__init__.py
sq_codec/codec.py
sq_codec/en_codec.py
sq_codec/layers.py
sq_codec/local_trans.py
sq_codec/modules.py
sq_codec/quantize.py
sq_codec/base/__init__.py
sq_codec/base/config.py
sq_codec/base/nn/__init__.py
sq_codec/base/nn/layers.py
sq_codec/base/nn/module.py
sq_codec/base/nn/utils.py
sq_codec/base/utils/__init__.py
sq_codec/base/utils/iter.py
sq_codec/base/utils/module.py
sq_codec/configs/0k75bps.toml
sq_codec/configs/12kbps.toml
sq_codec/configs/12kbps_24khz.toml
sq_codec/configs/1k5bps.toml
sq_codec/configs/24kbps_24khz.toml
sq_codec/configs/3kbps.toml
sq_codec/configs/6kbps.toml
sq_codec/tconv/__init__.py
sq_codec/tconv/base.py
sq_codec/tconv/t_first.py
sq_codec/tconv/t_last.py
sq_codec-0.0.1.dist-info/METADATA
sq_codec-0.0.1.dist-info/WHEEL
sq_codec-0.0.1.dist-info/RECORD
