Metadata-Version: 2.4
Name: sq_codec
Version: 0.0.1
Summary: SQCodec: A nerual audio codec with one quantizer
Project-URL: Documentation, https://github.com/zhai-lw/SQCodec#readme
Project-URL: Repository, https://github.com/zhai-lw/SQCodec.git
Project-URL: Issues, https://github.com/zhai-lw/SQCodec/issues
Project-URL: DOWNLOAD, https://huggingface.co/zhai-lw/SQCodec
Author-email: Linwei Zhai <zhai_lw@outlook.com>
License-Expression: MIT
Keywords: artificial intelligence,audio codec,deep learning,pytorch
Classifier: Development Status :: 4 - Beta
Classifier: Intended Audience :: Developers
Classifier: Programming Language :: Python
Classifier: Topic :: Scientific/Engineering :: Artificial Intelligence
Requires-Python: >=3.11
Requires-Dist: local-attention
Requires-Dist: more-itertools
Requires-Dist: pydantic-settings
Requires-Dist: torch>=2.0
Requires-Dist: vector-quantize-pytorch
Provides-Extra: examples
Requires-Dist: librosa; extra == 'examples'
